trailwatch/__init__.py
trailwatch/config.py
trailwatch/connectors/__init__.py
trailwatch/connectors/aws/__init__.py
trailwatch/connectors/aws/api.py
trailwatch/connectors/aws/connector.py
trailwatch/connectors/aws/handler.py
trailwatch/connectors/base.py
trailwatch/connectors/salesforce/__init__.py
trailwatch/connectors/salesforce/connector.py
trailwatch/context.py
trailwatch/exceptions.py
trailwatch-1.0.1.dist-info/LICENSE
trailwatch-1.0.1.dist-info/METADATA
trailwatch-1.0.1.dist-info/WHEEL
trailwatch-1.0.1.dist-info/RECORD
