Metadata-Version: 2.1
Name: trailwatch
Version: 1.0.1
Summary: Python SDK for TrailWatch by Kicksaw
Home-page: https://www.kicksaw.com/
License: Apache-2.0
Author: George Bocharov
Author-email: george@kicksaw.com
Requires-Python: >=3.10,<4.0
Classifier: License :: OSI Approved :: Apache Software License
Classifier: Programming Language :: Python :: 3
Classifier: Programming Language :: Python :: 3.10
Classifier: Programming Language :: Python :: 3.11
Provides-Extra: salesforce
Requires-Dist: requests (>=2.28.2,<3.0.0)
Requires-Dist: simple-salesforce (>=1.12.3,<2.0.0) ; extra == "salesforce"
Project-URL: Repository, https://github.com/Kicksaw-Consulting/trailwatch-python-sdk
